{
  "workflow": {
    "unique_name": "definition_workflow_01M2FIQ8COLYA7BMDsc3UeOgYjJxoF9WFZ1",
    "name": "0012 - Secure Endpoint - Threat Hunting Events to Incidents",
    "title": "0012 - Secure Endpoint - Threat Hunting Events to Incidents",
    "type": "generic.workflow",
    "base_type": "workflow",
    "variables": [
      {
        "schema_id": "datatype.string",
        "properties": {
          "value": "",
          "scope": "local",
          "name": "Secure Endpoint Environment URL",
          "type": "datatype.string",
          "description": "Placeholder for the URL of the Secure Endpoint environment being used. You don't need to provide this, it will be fetched automatically",
          "is_required": false,
          "is_invisible": false
        },
        "unique_name": "variable_workflow_01M9UUWLBYOWM1bFFn94eaBo65H4QZ2vS0r",
        "object_type": "variable_workflow"
      },
      {
        "schema_id": "datatype.string",
        "properties": {
          "value": "",
          "scope": "local",
          "name": "SecureX Environment URL",
          "type": "datatype.string",
          "description": "Placeholder for the URL of the SecureX environment being used. You don't need to provide this, it will be fetched automatically",
          "is_required": false,
          "is_invisible": false
        },
        "unique_name": "variable_workflow_01M9V6I4PRNX01dXKElTmBbBAetvFLHjo5A",
        "object_type": "variable_workflow"
      }
    ],
    "properties": {
      "atomic": {
        "is_atomic": false
      },
      "delete_workflow_instance": false,
      "description": "This workflow periodically checks a Secure Endpoint instance for SecureX Threat Hunting events. When an event is returned, the workflow collects information from it and creates a casebook and incident in Threat Response to document what happened. This workflow is designed to run every 5 minutes on a schedule.\n\nTarget Group: Default TargetGroup\n\nTargets: AMP_Target, CTR_API, CTR_For_Access_Token, Private_CTIA_Target\n\nSteps:\n[] Detect the region/environment being used\n[] Calculate date/times\n[] Fetch events from Secure Endpoint\n[] Check if events were returned, if not end the workflow\n[] For each event:\n[]\u003e Extract the event's information\n[]\u003e Format the information for Threat Response\n[]\u003e Create an incident, casebook, and sighting\n\nMore information: https://cs.co/SXO_docs",
      "display_name": "0012 - Secure Endpoint - Threat Hunting Events to Incidents",
      "runtime_user": {
        "override_target_runtime_user": false,
        "specify_on_workflow_start": false,
        "target_default": true
      },
      "target": {
        "execute_on_target_group": true,
        "target_group": {
          "target_group_id": "target_group_01EJ0TQWPQWBD0qiWqClJKj9FOzwiZRfOFH",
          "run_on_all_targets": false,
          "selected_target_types": [
            "web-service.endpoint"
          ],
          "use_criteria": {
            "choose_target_using_algorithm": "choose_first_with_matching_criteria",
            "conditions": [
              {
                "operator": "eqi",
                "left_operand": "$targetgroup.web-service endpoint.input.display_name$",
                "right_operand": "Private_CTIA_Target"
              }
            ]
          }
        }
      }
    },
    "object_type": "definition_workflow",
    "actions": [
      {
        "unique_name": "definition_activity_01M9UUZC8BOQQ1puYUt6UjUJSCaFkByoaxe",
        "name": "Condition Block",
        "title": "Set the environment URL",
        "type": "logic.if_else",
        "base_type": "activity",
        "properties": {
          "continue_on_failure": false,
          "display_name": "Set the environment URL",
          "skip_execution": false
        },
        "object_type": "definition_activity",
        "blocks": [
          {
            "unique_name": "definition_activity_01M9UUZN8S8X41kyMb3nN8vNqGQqd2jctLm",
            "name": "Condition Branch",
            "title": "PROD-NAM",
            "type": "logic.condition_block",
            "base_type": "activity",
            "properties": {
              "condition": {
                "left_operand": "$env.variable_01A6C871LSO9A26D0zcBjJoAKgRglrC10aG.env.variable_01A6C871LSO9A26D0zcBjJoAKgRglrC10aG$",
                "operator": "eqi",
                "right_operand": "prod-nam"
              },
              "continue_on_failure": false,
              "display_name": "PROD-NAM",
              "skip_execution": false
            },
            "object_type": "definition_activity",
            "actions": [
              {
                "unique_name": "definition_activity_01M9UV1OPV4944BkTgn1ToySDzIJ5vTR3gO",
                "name": "Set Variables",
                "title": "Set local environment variable",
                "type": "core.set_multiple_variables",
                "base_type": "activity",
                "properties": {
                  "continue_on_failure": false,
                  "display_name": "Set local environment variable",
                  "skip_execution": false,
                  "variables_to_update": [
                    {
                      "variable_to_update": "$workflow.definition_workflow_01M2FIQ8COLYA7BMDsc3UeOgYjJxoF9WFZ1.local.variable_workflow_01M9UUWLBYOWM1bFFn94eaBo65H4QZ2vS0r$",
                      "variable_value_new": "console.amp.cisco.com"
                    },
                    {
                      "variable_to_update": "$workflow.definition_workflow_01M2FIQ8COLYA7BMDsc3UeOgYjJxoF9WFZ1.local.variable_workflow_01M9V6I4PRNX01dXKElTmBbBAetvFLHjo5A$",
                      "variable_value_new": "securex-ao.us.security.cisco.com"
                    }
                  ]
                },
                "object_type": "definition_activity"
              }
            ]
          },
          {
            "unique_name": "definition_activity_01M9UVY47JOBD74Wv3rZLDxKViNsTGvJY7g",
            "name": "Condition Branch",
            "title": "PROD-EU",
            "type": "logic.condition_block",
            "base_type": "activity",
            "properties": {
              "condition": {
                "left_operand": "$env.variable_01A6C871LSO9A26D0zcBjJoAKgRglrC10aG.env.variable_01A6C871LSO9A26D0zcBjJoAKgRglrC10aG$",
                "operator": "eqi",
                "right_operand": "prod-eu"
              },
              "continue_on_failure": false,
              "display_name": "PROD-EU",
              "skip_execution": false
            },
            "object_type": "definition_activity",
            "actions": [
              {
                "unique_name": "definition_activity_01M9UVY56T64E78OkiiLlER7mtMq8UT0q3Y",
                "name": "Set Variables",
                "title": "Set local environment variable",
                "type": "core.set_multiple_variables",
                "base_type": "activity",
                "properties": {
                  "continue_on_failure": false,
                  "display_name": "Set local environment variable",
                  "skip_execution": false,
                  "variables_to_update": [
                    {
                      "variable_to_update": "$workflow.definition_workflow_01M2FIQ8COLYA7BMDsc3UeOgYjJxoF9WFZ1.local.variable_workflow_01M9UUWLBYOWM1bFFn94eaBo65H4QZ2vS0r$",
                      "variable_value_new": "console.eu.amp.cisco.com"
                    },
                    {
                      "variable_to_update": "$workflow.definition_workflow_01M2FIQ8COLYA7BMDsc3UeOgYjJxoF9WFZ1.local.variable_workflow_01M9V6I4PRNX01dXKElTmBbBAetvFLHjo5A$",
                      "variable_value_new": "securex-ao.eu.security.cisco.com"
                    }
                  ]
                },
                "object_type": "definition_activity"
              }
            ]
          },
          {
            "unique_name": "definition_activity_01M9UW6P01WJ26DM8DO1w0DOC0gPr2ugQ2B",
            "name": "Condition Branch",
            "title": "PROD-APJC",
            "type": "logic.condition_block",
            "base_type": "activity",
            "properties": {
              "condition": {
                "left_operand": "$env.variable_01A6C871LSO9A26D0zcBjJoAKgRglrC10aG.env.variable_01A6C871LSO9A26D0zcBjJoAKgRglrC10aG$",
                "operator": "eqi",
                "right_operand": "prod-apjc"
              },
              "continue_on_failure": false,
              "display_name": "PROD-APJC",
              "skip_execution": false
            },
            "object_type": "definition_activity",
            "actions": [
              {
                "unique_name": "definition_activity_01M9UW6PYQVBZ6T9gn6spU3mCHYkC2cwWHs",
                "name": "Set Variables",
                "title": "Set local environment variable",
                "type": "core.set_multiple_variables",
                "base_type": "activity",
                "properties": {
                  "continue_on_failure": false,
                  "display_name": "Set local environment variable",
                  "skip_execution": false,
                  "variables_to_update": [
                    {
                      "variable_to_update": "$workflow.definition_workflow_01M2FIQ8COLYA7BMDsc3UeOgYjJxoF9WFZ1.local.variable_workflow_01M9UUWLBYOWM1bFFn94eaBo65H4QZ2vS0r$",
                      "variable_value_new": "console.apjc.amp.cisco.com"
                    },
                    {
                      "variable_to_update": "$workflow.definition_workflow_01M2FIQ8COLYA7BMDsc3UeOgYjJxoF9WFZ1.local.variable_workflow_01M9V6I4PRNX01dXKElTmBbBAetvFLHjo5A$",
                      "variable_value_new": "securex-ao.apjc.security.cisco.com"
                    }
                  ]
                },
                "object_type": "definition_activity"
              }
            ]
          }
        ]
      },
      {
        "unique_name": "definition_activity_01M3BRETU8GV53mzHaJZUG3XeZk2329aSPM",
        "name": "Group",
        "title": "Calculate date and fetch events",
        "type": "logic.group",
        "base_type": "activity",
        "properties": {
          "continue_on_failure": false,
          "display_name": "Calculate date and fetch events",
          "skip_execution": false
        },
        "object_type": "definition_activity",
        "actions": [
          {
            "unique_name": "definition_activity_01M2FMEH8KT8J2yZdHkQxwFTue0O3wYOjOd",
            "name": "Calculate Date",
            "title": "Calculate time 5 minutes ago",
            "type": "core.calculate_date",
            "base_type": "activity",
            "properties": {
              "adjustment": -300,
              "continue_on_failure": false,
              "display_name": "Calculate time 5 minutes ago",
              "original_date": "$workflow.definition_workflow_01M2FIQ8COLYA7BMDsc3UeOgYjJxoF9WFZ1.output.start_time$",
              "skip_execution": false
            },
            "object_type": "definition_activity"
          },
          {
            "unique_name": "definition_activity_01M2FNMLGFHLF1cLSeDWpJZ6HscKs06pLb4",
            "name": "Format Date",
            "title": "Format date for Secure Endpoint",
            "type": "core.format_date",
            "base_type": "activity",
            "properties": {
              "continue_on_failure": false,
              "display_name": "Format date for Secure Endpoint",
              "format_string": "2006-01-02T15:04:05Z07:00",
              "original_date": "$activity.definition_activity_01M2FMEH8KT8J2yZdHkQxwFTue0O3wYOjOd.output.result$",
              "skip_execution": false,
              "use_custom_format": false
            },
            "object_type": "definition_activity"
          },
          {
            "unique_name": "definition_activity_01M2FSVM6B9GN5udSlhUWVgye89hpBY0bgT",
            "name": "HTTP Request",
            "title": "Get recent Threat Hunting events",
            "type": "web-service.http_request",
            "base_type": "activity",
            "properties": {
              "action_timeout": 180,
              "allow_auto_redirect": true,
              "content_type": "application/json",
              "continue_on_error_status_code": false,
              "continue_on_failure": false,
              "display_name": "Get recent Threat Hunting events",
              "method": "GET",
              "relative_url": "events?start_date=$activity.definition_activity_01M2FNMLGFHLF1cLSeDWpJZ6HscKs06pLb4.output.result$\u0026event_type=1107296344",
              "runtime_user": {
                "target_default": true
              },
              "skip_execution": false,
              "target": {
                "override_workflow_target_group_criteria": true,
                "target_group": {
                  "use_criteria": {
                    "choose_target_using_algorithm": "choose_first_with_matching_criteria",
                    "conditions": [
                      {
                        "left_operand": "$targetgroup.web-service endpoint.input.display_name$",
                        "operator": "eqi",
                        "right_operand": "AMP_Target"
                      }
                    ]
                  }
                }
              }
            },
            "object_type": "definition_activity"
          },
          {
            "unique_name": "definition_activity_01MGS5QYFG0Z71lwFDHXsCe4Qty1vvu8qMZ",
            "name": "Condition Block",
            "title": "Was the request successful?",
            "type": "logic.if_else",
            "base_type": "activity",
            "properties": {
              "continue_on_failure": false,
              "display_name": "Was the request successful?",
              "skip_execution": false
            },
            "object_type": "definition_activity",
            "blocks": [
              {
                "unique_name": "definition_activity_01MGS5R9ON6ZQ1ckRpg9M1UPoz3tLmQpf5C",
                "name": "Condition Branch",
                "title": "No",
                "type": "logic.condition_block",
                "base_type": "activity",
                "properties": {
                  "condition": {
                    "left_operand": "$activity.definition_activity_01M2FSVM6B9GN5udSlhUWVgye89hpBY0bgT.output.status_code$",
                    "operator": "ne",
                    "right_operand": 200
                  },
                  "continue_on_failure": false,
                  "display_name": "No",
                  "skip_execution": false
                },
                "object_type": "definition_activity",
                "actions": [
                  {
                    "unique_name": "definition_activity_01MGS659YH6Q81dQjbOMoteDOyGdU8gVHaO",
                    "name": "Completed",
                    "title": "Failed",
                    "type": "logic.completed",
                    "base_type": "activity",
                    "properties": {
                      "completion_type": "failed-completed",
                      "continue_on_failure": false,
                      "display_name": "Failed",
                      "result_message": "Failed to fetch Threat Hunting events from Secure Endpoint\n\nStatus code: $activity.definition_activity_01M2FSVM6B9GN5udSlhUWVgye89hpBY0bgT.output.status_code$\nResponse body: $activity.definition_activity_01M2FSVM6B9GN5udSlhUWVgye89hpBY0bgT.output.response_body$",
                      "skip_execution": false
                    },
                    "object_type": "definition_activity"
                  }
                ]
              }
            ]
          }
        ]
      },
      {
        "unique_name": "definition_activity_01M2G2ZKBRKR81KCCJbk52LxFKcoMYhv4kF",
        "name": "JSONPath Query",
        "title": "Extract event count",
        "type": "corejava.jsonpathquery",
        "base_type": "activity",
        "properties": {
          "action_timeout": 180,
          "continue_on_failure": false,
          "display_name": "Extract event count",
          "input_json": "$activity.definition_activity_01M2FSVM6B9GN5udSlhUWVgye89hpBY0bgT.output.response_body$",
          "jsonpath_queries": [
            {
              "jsonpath_query": "$.metadata.results.total",
              "jsonpath_query_name": "resultCount",
              "jsonpath_query_type": "integer"
            }
          ],
          "skip_execution": false
        },
        "object_type": "definition_activity"
      },
      {
        "unique_name": "definition_activity_01M2G4KRAHP3T3uT7OTqwEyJXBwMPFUIe39",
        "name": "Condition Block",
        "title": "Were there any events?",
        "type": "logic.if_else",
        "base_type": "activity",
        "properties": {
          "continue_on_failure": false,
          "display_name": "Were there any events?",
          "skip_execution": false
        },
        "object_type": "definition_activity",
        "blocks": [
          {
            "unique_name": "definition_activity_01M2G4LBFG2KI4XDJkFHtTY3CSQogFjtxn4",
            "name": "Condition Branch",
            "title": "No",
            "type": "logic.condition_block",
            "base_type": "activity",
            "properties": {
              "condition": {
                "left_operand": "$activity.definition_activity_01M2G2ZKBRKR81KCCJbk52LxFKcoMYhv4kF.output.jsonpath_queries.resultCount$",
                "operator": "eq",
                "right_operand": 0
              },
              "continue_on_failure": false,
              "display_name": "No",
              "skip_execution": false
            },
            "object_type": "definition_activity",
            "actions": [
              {
                "unique_name": "definition_activity_01M2G5TGUNR232rxc3H7aPDtsnVmqK4jYJ7",
                "name": "Completed",
                "title": "End the workflow",
                "type": "logic.completed",
                "base_type": "activity",
                "properties": {
                  "completion_type": "succeeded",
                  "continue_on_failure": false,
                  "display_name": "End the workflow",
                  "result_message": "No Threat Hunting events were returned by Secure Endpoint",
                  "skip_execution": false
                },
                "object_type": "definition_activity"
              }
            ]
          }
        ]
      },
      {
        "unique_name": "definition_activity_01M3BS00S09PV2vshDrSibIpgrvNedmAUwR",
        "name": "Group",
        "title": "Parse events to incidents",
        "type": "logic.group",
        "base_type": "activity",
        "properties": {
          "continue_on_failure": false,
          "display_name": "Parse events to incidents",
          "skip_execution": false
        },
        "object_type": "definition_activity",
        "actions": [
          {
            "unique_name": "definition_activity_01M2GB86L87U40FewVZAMkMED9Jm4Nsttfw",
            "name": "Read Table from JSON",
            "title": "Convert events to table",
            "type": "corejava.read_table_from_json",
            "base_type": "activity",
            "properties": {
              "action_timeout": 180,
              "continue_on_failure": false,
              "display_name": "Convert events to table",
              "input_json": "$activity.definition_activity_01M2FSVM6B9GN5udSlhUWVgye89hpBY0bgT.output.response_body$",
              "jsonpath_query": "$.data",
              "persist_output": false,
              "populate_columns": false,
              "skip_execution": false,
              "table_columns": [
                {
                  "column_name": "computer",
                  "column_type": "string"
                },
                {
                  "column_name": "threat_hunting",
                  "column_type": "string"
                },
                {
                  "column_name": "severity",
                  "column_type": "string"
                },
                {
                  "column_name": "date",
                  "column_type": "string"
                }
              ]
            },
            "object_type": "definition_activity"
          },
          {
            "unique_name": "definition_activity_01M3ABFBZDJQM0lMI1uGosP2g1O9r1kM7SZ",
            "name": "For Each",
            "title": "For each event",
            "type": "logic.for_each",
            "base_type": "activity",
            "properties": {
              "continue_on_failure": false,
              "display_name": "For each event",
              "skip_execution": false,
              "source_array": "$activity.definition_activity_01M2GB86L87U40FewVZAMkMED9Jm4Nsttfw.output.read_table_from_json$"
            },
            "object_type": "definition_activity",
            "actions": [
              {
                "unique_name": "definition_activity_01M43N8FP6UGF5dRHRzgOqu0hXDEBzFqBbn",
                "name": "Group",
                "title": "Extract and format event data",
                "type": "logic.group",
                "base_type": "activity",
                "properties": {
                  "continue_on_failure": false,
                  "display_name": "Extract and format event data",
                  "skip_execution": false
                },
                "object_type": "definition_activity",
                "actions": [
                  {
                    "unique_name": "definition_activity_01M3CCEV9XQ760A8j96bTWyRSHwzfkmHuqk",
                    "name": "JSONPath Query",
                    "title": "Extract computer attributes",
                    "type": "corejava.jsonpathquery",
                    "base_type": "activity",
                    "properties": {
                      "action_timeout": 180,
                      "continue_on_failure": false,
                      "display_name": "Extract computer attributes",
                      "input_json": "$activity.definition_activity_01M3ABFBZDJQM0lMI1uGosP2g1O9r1kM7SZ.input.source_array[@].computer$",
                      "jsonpath_queries": [
                        {
                          "jsonpath_query": "$.connector_guid",
                          "jsonpath_query_name": "connector_guid",
                          "jsonpath_query_type": "string"
                        },
                        {
                          "jsonpath_query": "$.hostname",
                          "jsonpath_query_name": "hostname",
                          "jsonpath_query_type": "string"
                        }
                      ],
                      "skip_execution": false
                    },
                    "object_type": "definition_activity"
                  },
                  {
                    "unique_name": "definition_activity_01M3CD9CQM8TB2G97hkNtJoO6xSlm7tKjAG",
                    "name": "JSONPath Query",
                    "title": "Extract threat hunting attributes",
                    "type": "corejava.jsonpathquery",
                    "base_type": "activity",
                    "properties": {
                      "action_timeout": 180,
                      "continue_on_failure": true,
                      "display_name": "Extract threat hunting attributes",
                      "input_json": "$activity.definition_activity_01M3ABFBZDJQM0lMI1uGosP2g1O9r1kM7SZ.input.source_array[@].threat_hunting$",
                      "jsonpath_queries": [
                        {
                          "jsonpath_query": "$.incident_title",
                          "jsonpath_query_name": "incident_title",
                          "jsonpath_query_type": "string"
                        },
                        {
                          "jsonpath_query": "$.incident_summary",
                          "jsonpath_query_name": "incident_summary",
                          "jsonpath_query_type": "string"
                        },
                        {
                          "jsonpath_query": "$.incident_remediation",
                          "jsonpath_query_name": "incident_remediation",
                          "jsonpath_query_type": "string"
                        },
                        {
                          "jsonpath_query": "$.incident_report_guid",
                          "jsonpath_query_name": "incident_report_guid",
                          "jsonpath_query_type": "string"
                        }
                      ],
                      "skip_execution": false
                    },
                    "object_type": "definition_activity"
                  },
                  {
                    "unique_name": "definition_activity_01M9UTCHKQWDB3pANbXS68B6cdgbGk88n4n",
                    "name": "Condition Block",
                    "title": "Were we able to extract threat hunting information?",
                    "type": "logic.if_else",
                    "base_type": "activity",
                    "properties": {
                      "continue_on_failure": false,
                      "display_name": "Were we able to extract threat hunting information?",
                      "skip_execution": false
                    },
                    "object_type": "definition_activity",
                    "blocks": [
                      {
                        "unique_name": "definition_activity_01M9UTD34JEDR2pGBK9ZkMNT6zK1DnvgzBR",
                        "name": "Condition Branch",
                        "title": "No",
                        "type": "logic.condition_block",
                        "base_type": "activity",
                        "properties": {
                          "condition": {
                            "left_operand": "$activity.definition_activity_01M3CD9CQM8TB2G97hkNtJoO6xSlm7tKjAG.output.succeeded$",
                            "operator": "eq",
                            "right_operand": false
                          },
                          "continue_on_failure": false,
                          "display_name": "No",
                          "skip_execution": false
                        },
                        "object_type": "definition_activity",
                        "actions": [
                          {
                            "unique_name": "definition_activity_01M9UTF7JJL1T3v5WtiOLEdndS5rOCVbSsv",
                            "name": "Continue",
                            "title": "Skip this event",
                            "type": "logic.continue",
                            "base_type": "activity",
                            "properties": {
                              "continue_on_failure": false,
                              "display_name": "Skip this event",
                              "skip_execution": false
                            },
                            "object_type": "definition_activity"
                          }
                        ]
                      }
                    ]
                  },
                  {
                    "unique_name": "definition_activity_01M3TUEBIN5VH6ZNCs9OaFTYIXDpX9PEYQ9",
                    "name": "Replace String",
                    "title": "Format incident summary",
                    "type": "core.replacestring",
                    "base_type": "activity",
                    "properties": {
                      "continue_on_failure": false,
                      "description": "Change html new line and list code to markdown supported text.",
                      "display_name": "Format incident summary",
                      "input_string": "$activity.definition_activity_01M3CD9CQM8TB2G97hkNtJoO6xSlm7tKjAG.output.jsonpath_queries.incident_summary$",
                      "replace_list": [
                        {
                          "replaced_string": "\\n-",
                          "replacement_string": "\n*"
                        },
                        {
                          "replaced_string": "\\n",
                          "replacement_string": "\n"
                        }
                      ],
                      "skip_execution": false
                    },
                    "object_type": "definition_activity"
                  },
                  {
                    "unique_name": "definition_activity_01M432KUBF88N5G0pyoYwyLUWHF2EY2ffo8",
                    "name": "Replace String",
                    "title": "Format incident remediation",
                    "type": "core.replacestring",
                    "base_type": "activity",
                    "properties": {
                      "continue_on_failure": false,
                      "description": "Change html new line and list code to markdown supported text.",
                      "display_name": "Format incident remediation",
                      "input_string": "$activity.definition_activity_01M3CD9CQM8TB2G97hkNtJoO6xSlm7tKjAG.output.jsonpath_queries.incident_remediation$",
                      "replace_list": [
                        {
                          "replaced_string": "\\n-",
                          "replacement_string": "\n*"
                        },
                        {
                          "replaced_string": "\\n",
                          "replacement_string": "\n"
                        }
                      ],
                      "skip_execution": false
                    },
                    "object_type": "definition_activity"
                  }
                ]
              },
              {
                "unique_name": "definition_activity_01M43NPBSUDU40YNLUnChoMgEsAqlXKuI1k",
                "name": "Group",
                "title": "Create Threat Response objects",
                "type": "logic.group",
                "base_type": "activity",
                "properties": {
                  "continue_on_failure": false,
                  "display_name": "Create Threat Response objects",
                  "skip_execution": false
                },
                "object_type": "definition_activity",
                "actions": [
                  {
                    "unique_name": "definition_activity_01M3CAEF34IHL369NDSCxUj3Y0wzWgIHqDV",
                    "name": "Threat Response v2 - Generate Access Token",
                    "title": "Threat Response v2 - Generate Access Token",
                    "type": "workflow.atomic_workflow",
                    "base_type": "subworkflow",
                    "properties": {
                      "continue_on_failure": false,
                      "display_name": "Threat Response v2 - Generate Access Token",
                      "runtime_user": {
                        "target_default": true
                      },
                      "skip_execution": false,
                      "target": {
                        "override_workflow_target_group_criteria": true,
                        "target_group": {
                          "run_on_all_targets": false,
                          "use_criteria": {
                            "choose_target_using_algorithm": "choose_first_with_matching_criteria",
                            "conditions": [
                              {
                                "left_operand": "$targetgroup.web-service endpoint.input.display_name$",
                                "operator": "eqi",
                                "right_operand": "CTR_For_Access_Token"
                              }
                            ]
                          }
                        }
                      },
                      "workflow_id": "definition_workflow_01KWJ2ISZTF2V6ibRYe7FZ7sOuycDOpnwss"
                    },
                    "object_type": "definition_activity"
                  },
                  {
                    "unique_name": "definition_activity_01M3CBF64F04V67EJkexKkUoYfvpj6jhQk9",
                    "name": "Threat Response v2 - Create Incident",
                    "title": "Threat Response v2 - Create Incident",
                    "type": "workflow.atomic_workflow",
                    "base_type": "subworkflow",
                    "properties": {
                      "continue_on_failure": false,
                      "display_name": "Threat Response v2 - Create Incident",
                      "input": {
                        "variable_workflow_01KVVWMAKJ5X54vaAuNkKq259VyiO5JCeuC": "$activity.definition_activity_01M3CAEF34IHL369NDSCxUj3Y0wzWgIHqDV.output.variable_workflow_01KWJ2ISHZ9753Hoi7x9S5EPpucAbm53HHF$",
                        "variable_workflow_01KVVWMAKJ9HX4TuMb2g74UqzpRLRxjwlwm": "$activity.definition_activity_01M3CD9CQM8TB2G97hkNtJoO6xSlm7tKjAG.output.jsonpath_queries.incident_title$ ($activity.definition_activity_01M3CCEV9XQ760A8j96bTWyRSHwzfkmHuqk.output.jsonpath_queries.hostname$)",
                        "variable_workflow_01KVVWMAKJBSF1Fxv8uLSCRGpOJCxkue4OH": "* [View Incident in Secure Endpoint](https://$workflow.definition_workflow_01M2FIQ8COLYA7BMDsc3UeOgYjJxoF9WFZ1.local.variable_workflow_01M9UUWLBYOWM1bFFn94eaBo65H4QZ2vS0r$/threat_hunting/incidents/$activity.definition_activity_01M3CD9CQM8TB2G97hkNtJoO6xSlm7tKjAG.output.jsonpath_queries.incident_report_guid$)\n* [View Endpoint Trajectory](https://$workflow.definition_workflow_01M2FIQ8COLYA7BMDsc3UeOgYjJxoF9WFZ1.local.variable_workflow_01M9UUWLBYOWM1bFFn94eaBo65H4QZ2vS0r$/computers/$activity.definition_activity_01M3CCEV9XQ760A8j96bTWyRSHwzfkmHuqk.output.jsonpath_queries.connector_guid$/trajectory2)\n* [View Workflow Run](https://$workflow.definition_workflow_01M2FIQ8COLYA7BMDsc3UeOgYjJxoF9WFZ1.local.variable_workflow_01M9V6I4PRNX01dXKElTmBbBAetvFLHjo5A$/orch-ui/runs/$workflow.definition_workflow_01M2FIQ8COLYA7BMDsc3UeOgYjJxoF9WFZ1.output.instance_id$)\n\n***\n\n$activity.definition_activity_01M3TUEBIN5VH6ZNCs9OaFTYIXDpX9PEYQ9.output.result_string$\n\n***\n\n$activity.definition_activity_01M432KUBF88N5G0pyoYwyLUWHF2EY2ffo8.output.result_string$",
                        "variable_workflow_01KWIVDCZ7VJU1t9jPK4nZnnwHqnllu7dJm": "New",
                        "variable_workflow_01KWIVQVGZKUC0vUPbm3oCvqsYVV036tieP": "High",
                        "variable_workflow_01LFBWLGJNHPS450Wh1dwGf1Xqot6KHUTwY": "amber"
                      },
                      "runtime_user": {
                        "target_default": true
                      },
                      "skip_execution": false,
                      "target": {
                        "use_workflow_target_group": true
                      },
                      "workflow_id": "definition_workflow_01KVVWMB2UTRF5uVHVH9DtiT6vgIfnzTdRS"
                    },
                    "object_type": "definition_activity"
                  },
                  {
                    "unique_name": "definition_activity_01M3CGZZURE5A054rYSrOWqw7CctziarVJg",
                    "name": "Threat Response v2 - Create Casebook",
                    "title": "Threat Response v2 - Create Casebook",
                    "type": "workflow.atomic_workflow",
                    "base_type": "subworkflow",
                    "properties": {
                      "continue_on_failure": false,
                      "display_name": "Threat Response v2 - Create Casebook",
                      "input": {
                        "variable_workflow_01KVOGF4J481T6SCd7uh5fW7n47Q712nleJ": "[{ \"type\": \"amp_computer_guid\", \"value\": \"$activity.definition_activity_01M3CCEV9XQ760A8j96bTWyRSHwzfkmHuqk.output.jsonpath_queries.connector_guid$\" }, { \"type\": \"hostname\", \"value\": \"$activity.definition_activity_01M3CCEV9XQ760A8j96bTWyRSHwzfkmHuqk.output.jsonpath_queries.hostname$\" }]",
                        "variable_workflow_01KVOGF4J4FZC0jmaR42b1FbIzVZA19KbYL": "* [View Incident in Secure Endpoint](https://$workflow.definition_workflow_01M2FIQ8COLYA7BMDsc3UeOgYjJxoF9WFZ1.local.variable_workflow_01M9UUWLBYOWM1bFFn94eaBo65H4QZ2vS0r$/threat_hunting/incidents/$activity.definition_activity_01M3CD9CQM8TB2G97hkNtJoO6xSlm7tKjAG.output.jsonpath_queries.incident_report_guid$)\n* [View Endpoint Trajectory](https://$workflow.definition_workflow_01M2FIQ8COLYA7BMDsc3UeOgYjJxoF9WFZ1.local.variable_workflow_01M9UUWLBYOWM1bFFn94eaBo65H4QZ2vS0r$/computers/$activity.definition_activity_01M3CCEV9XQ760A8j96bTWyRSHwzfkmHuqk.output.jsonpath_queries.connector_guid$/trajectory2)\n* [View Workflow Run](https://$workflow.definition_workflow_01M2FIQ8COLYA7BMDsc3UeOgYjJxoF9WFZ1.local.variable_workflow_01M9V6I4PRNX01dXKElTmBbBAetvFLHjo5A$/orch-ui/runs/$workflow.definition_workflow_01M2FIQ8COLYA7BMDsc3UeOgYjJxoF9WFZ1.output.instance_id$)\n\n$activity.definition_activity_01M432KUBF88N5G0pyoYwyLUWHF2EY2ffo8.output.result_string$",
                        "variable_workflow_01KVOGF4J4IG81TQKFjqzLlnFJwiiNwXwSq": "$activity.definition_activity_01M3CAEF34IHL369NDSCxUj3Y0wzWgIHqDV.output.variable_workflow_01KWJ2ISHZ9753Hoi7x9S5EPpucAbm53HHF$",
                        "variable_workflow_01KVOGF4J4JL52xC9ZXdjYwHt2SvRYkArli": "$activity.definition_activity_01M3CD9CQM8TB2G97hkNtJoO6xSlm7tKjAG.output.jsonpath_queries.incident_title$ ($activity.definition_activity_01M3CCEV9XQ760A8j96bTWyRSHwzfkmHuqk.output.jsonpath_queries.hostname$)",
                        "variable_workflow_01KVOMXV9ERSV0M9j1WarflgSG8r5SpZ8b5": "A SecureX Threat Hunting event was detected in Secure Endpoint for host $activity.definition_activity_01M3CCEV9XQ760A8j96bTWyRSHwzfkmHuqk.output.jsonpath_queries.hostname$",
                        "variable_workflow_01LFBYQJV9FZA2THdEQrMftLyGiiHP65nUq": "amber"
                      },
                      "runtime_user": {
                        "target_default": true
                      },
                      "skip_execution": false,
                      "target": {
                        "use_workflow_target_group": true
                      },
                      "workflow_id": "definition_workflow_01KVOGF574Y291CRwQLNB1TtzEHDNwyUx7O"
                    },
                    "object_type": "definition_activity"
                  },
                  {
                    "unique_name": "definition_activity_01M3CH9XSSGZM5lbaHwTfVm5xBmJjmEgwh2",
                    "name": "Threat Response v2 - Create Relationship",
                    "title": "Threat Response v2 - Create Relationship",
                    "type": "workflow.atomic_workflow",
                    "base_type": "subworkflow",
                    "properties": {
                      "continue_on_failure": false,
                      "display_name": "Threat Response v2 - Create Relationship",
                      "input": {
                        "variable_workflow_01KWID476NLS63mQo7De2Wk9Q1WAJb0dJXe": "$activity.definition_activity_01M3CAEF34IHL369NDSCxUj3Y0wzWgIHqDV.output.variable_workflow_01KWJ2ISHZ9753Hoi7x9S5EPpucAbm53HHF$",
                        "variable_workflow_01KWID476NNBL4xUNZ1ze05KmIr6MTOd2tf": "related-to",
                        "variable_workflow_01KWID476NOW27YCzfBvT6jlpfoo4jDNQoS": "SecureX Threat Hunting Event",
                        "variable_workflow_01KWID476NRV53BPxHqiyGzSy3hiS50IIYt": "",
                        "variable_workflow_01KWIOPHDZHRM2nxENJ5E3iBUjDizSHzujd": "$activity.definition_activity_01M3CGZZURE5A054rYSrOWqw7CctziarVJg.output.variable_workflow_01KVOGF4J4HBH1AEO1b5YnhSpqUnFihUeXS$",
                        "variable_workflow_01KWIP24K2A5P6ag8merXYIrzb5KHnOSzU3": "$activity.definition_activity_01M3CBF64F04V67EJkexKkUoYfvpj6jhQk9.output.variable_workflow_01KVVWMAKJDWL0w7z086xbnRNZMwGcpxweP$",
                        "variable_workflow_01LFBZWJ98ZH426APtwKiW7OM9nNQMfT7IA": "amber"
                      },
                      "runtime_user": {
                        "target_default": true
                      },
                      "skip_execution": false,
                      "target": {
                        "use_workflow_target_group": true
                      },
                      "workflow_id": "definition_workflow_01KWID47SRHY30TYWU3BQSFODWA7PVO360x"
                    },
                    "object_type": "definition_activity"
                  },
                  {
                    "unique_name": "definition_activity_01M3UTX69JPU43VRcP9NASiFY5HOfQI53dj",
                    "name": "Threat Response v2 - Create Sighting",
                    "title": "Threat Response v2 - Create Sighting",
                    "type": "workflow.atomic_workflow",
                    "base_type": "subworkflow",
                    "properties": {
                      "continue_on_failure": false,
                      "display_name": "Threat Response v2 - Create Sighting",
                      "input": {
                        "variable_workflow_01KWI6XBXC36X5fDp4P3C4W39e3ii12zcYI": "Endpoint related to a SecureX Threat Hunting event",
                        "variable_workflow_01KWI6XBXC8MT4PhPchVEzUFUYhgJ5L37zI": "$activity.definition_activity_01M3CD9CQM8TB2G97hkNtJoO6xSlm7tKjAG.output.jsonpath_queries.incident_title$",
                        "variable_workflow_01KWI6XBXCB6Z7FBz7mVAbr2nQMRfJrB9h4": "$activity.definition_activity_01M3CAEF34IHL369NDSCxUj3Y0wzWgIHqDV.output.variable_workflow_01KWJ2ISHZ9753Hoi7x9S5EPpucAbm53HHF$",
                        "variable_workflow_01KWI8HQQALI75l9Rdg4OpEokFpKs35ZysU": "[{ \"type\": \"amp_computer_guid\", \"value\": \"$activity.definition_activity_01M3CCEV9XQ760A8j96bTWyRSHwzfkmHuqk.output.jsonpath_queries.connector_guid$\" }, {\"type\": \"hostname\", \"value\": \"$activity.definition_activity_01M3CCEV9XQ760A8j96bTWyRSHwzfkmHuqk.output.jsonpath_queries.hostname$\" }]",
                        "variable_workflow_01KWI98GQEUY83GabUEPdfqY7XaeitLae2F": "Medium",
                        "variable_workflow_01KWIBOK8V9E16FTFfn7IAUK0P0mHgXZrGT": "[{ \"type\": \"endpoint\", \"observables\": [{ \"type\": \"amp_computer_guid\", \"value\": \"$activity.definition_activity_01M3CCEV9XQ760A8j96bTWyRSHwzfkmHuqk.output.jsonpath_queries.connector_guid$\" }], \"observed_time\": {\"start_time\": \"$activity.definition_activity_01M3ABFBZDJQM0lMI1uGosP2g1O9r1kM7SZ.input.source_array[@].date$\" }}]",
                        "variable_workflow_01KWIYHA5ADVS34NX0EPNpeSYNtUj522l8P": "High",
                        "variable_workflow_01LFBXTCC6NTI4FkW9IYQZb6HAYE8EtHfl7": "amber"
                      },
                      "runtime_user": {
                        "target_default": true
                      },
                      "skip_execution": false,
                      "target": {
                        "use_workflow_target_group": true
                      },
                      "workflow_id": "definition_workflow_01KWI6XE6K5YD5I6K2wZF5Vp0M9FyXUl34y"
                    },
                    "object_type": "definition_activity"
                  },
                  {
                    "unique_name": "definition_activity_01M3CGLVU0T474EvUfFEhkr2wn5rdOX0cX5",
                    "name": "Threat Response v2 - Create Relationship",
                    "title": "Threat Response v2 - Create Relationship",
                    "type": "workflow.atomic_workflow",
                    "base_type": "subworkflow",
                    "properties": {
                      "continue_on_failure": false,
                      "display_name": "Threat Response v2 - Create Relationship",
                      "input": {
                        "variable_workflow_01KWID476NLS63mQo7De2Wk9Q1WAJb0dJXe": "$activity.definition_activity_01M3CAEF34IHL369NDSCxUj3Y0wzWgIHqDV.output.variable_workflow_01KWJ2ISHZ9753Hoi7x9S5EPpucAbm53HHF$",
                        "variable_workflow_01KWID476NNBL4xUNZ1ze05KmIr6MTOd2tf": "related-to",
                        "variable_workflow_01KWID476NOW27YCzfBvT6jlpfoo4jDNQoS": "",
                        "variable_workflow_01KWID476NRV53BPxHqiyGzSy3hiS50IIYt": "",
                        "variable_workflow_01KWIOPHDZHRM2nxENJ5E3iBUjDizSHzujd": "$activity.definition_activity_01M3UTX69JPU43VRcP9NASiFY5HOfQI53dj.output.variable_workflow_01KWI6XBXCA122ks58vY1MiMR3fTMolsjyC$",
                        "variable_workflow_01KWIP24K2A5P6ag8merXYIrzb5KHnOSzU3": "$activity.definition_activity_01M3CBF64F04V67EJkexKkUoYfvpj6jhQk9.output.variable_workflow_01KVVWMAKJDWL0w7z086xbnRNZMwGcpxweP$",
                        "variable_workflow_01LFBZWJ98ZH426APtwKiW7OM9nNQMfT7IA": "amber"
                      },
                      "runtime_user": {
                        "target_default": true
                      },
                      "skip_execution": false,
                      "target": {
                        "use_workflow_target_group": true
                      },
                      "workflow_id": "definition_workflow_01KWID47SRHY30TYWU3BQSFODWA7PVO360x"
                    },
                    "object_type": "definition_activity"
                  }
                ]
              }
            ]
          }
        ]
      }
    ],
    "categories": [
      "category_1BMfMXSnJMyt5Ihqi7rWJr5N8cf"
    ]
  },
  "triggers": {
    "triggerschedule_01M42X8Q76VUY7a5Dp7hWfwU49rUTydbRPa": {
      "workflow_id": "definition_workflow_01M2FIQ8COLYA7BMDsc3UeOgYjJxoF9WFZ1",
      "name": "Secure Endpoint Event Polling",
      "title": "",
      "lowercase_name": "schedule.secure_endpoint_event_polling",
      "type": "schedule",
      "base_type": "trigger",
      "ref_id": "schedule_01M9V3AE6WMAE7G8U2p3FQ76xYovrQLlwkV",
      "version": "",
      "disabled": true,
      "unique_name": "triggerschedule_01M42X8Q76VUY7a5Dp7hWfwU49rUTydbRPa",
      "object_type": "triggerschedule"
    }
  },
  "schedules": {
    "schedule_01M9V3AE6WMAE7G8U2p3FQ76xYovrQLlwkV": {
      "unique_name": "schedule_01M9V3AE6WMAE7G8U2p3FQ76xYovrQLlwkV",
      "name": "0012 - Secure Endpoint - Threat Hunting Events to Incidents",
      "description": "This schedule is used to check for new SecureX Threat Hunting events in Secure Endpoint",
      "type": "basic.schedule",
      "base_type": "schedule",
      "properties": {
        "calendar": "calendar_recurring_1BMfMWvgiDhSjBQ7hTSyvz3NyVZ",
        "timezone": "Etc/GMT+0",
        "starttime": "00:00",
        "interval_hours": 0,
        "interval_minutes": 5,
        "number_of_times": 288,
        "display_name": "0012 - Secure Endpoint - Threat Hunting Events to Incidents",
        "description": "This schedule is used to check for new SecureX Threat Hunting events in Secure Endpoint"
      },
      "version": "1.0.0",
      "object_type": "schedule"
    }
  },
  "target_groups": {
    "target_group_01EJ0TQWPQWBD0qiWqClJKj9FOzwiZRfOFH": {
      "unique_name": "target_group_01EJ0TQWPQWBD0qiWqClJKj9FOzwiZRfOFH",
      "name": "Default TargetGroup",
      "title": "Default TargetGroup",
      "type": "generic.target_group",
      "base_type": "target_group",
      "version": "1.0.0",
      "targets": [
        {
          "data_target_type": "web-service.endpoint",
          "view_target_type": "web-service.endpoint",
          "include_all_targets": true
        },
        {
          "data_target_type": "email.smtp_endpoint",
          "view_target_type": "email.smtp_endpoint",
          "include_all_targets": true
        },
        {
          "data_target_type": "terminal.endpoint",
          "view_target_type": "terminal.endpoint",
          "include_all_targets": true
        },
        {
          "data_target_type": "aws.endpoint",
          "view_target_type": "aws.endpoint",
          "include_all_targets": true
        }
      ],
      "object_type": "target_group"
    }
  },
  "atomic_workflows": [
    "definition_workflow_01KWI6XE6K5YD5I6K2wZF5Vp0M9FyXUl34y",
    "definition_workflow_01KVOGF574Y291CRwQLNB1TtzEHDNwyUx7O",
    "definition_workflow_01KWJ2ISZTF2V6ibRYe7FZ7sOuycDOpnwss",
    "definition_workflow_01KVVWMB2UTRF5uVHVH9DtiT6vgIfnzTdRS",
    "definition_workflow_01KWID47SRHY30TYWU3BQSFODWA7PVO360x"
  ]
}